src/__init__.py
src/cli/__init__.py
src/cli/__main__.py
src/cli/commands/__init__.py
src/cli/commands/assets.py
src/cli/commands/gains.py
src/cli/commands/household.py
src/cli/commands/lookalike.py
src/cli/commands/metrics.py
src/cli/commands/mine.py
src/cli/commands/mining.py
src/cli/commands/optimize.py
src/cli/commands/property_.py
src/cli/commands/rules.py
src/cli/commands/run.py
src/cli/commands/sample.py
src/core/__init__.py
src/core/audit.py
src/core/classify.py
src/core/config.py
src/core/deduce.py
src/core/dedupe.py
src/core/depreciation.py
src/core/household.py
src/core/metrics.py
src/core/mining.py
src/core/models.py
src/core/planning.py
src/core/property.py
src/core/rates.py
src/core/rules.py
src/core/trades.py
src/core/transfers.py
src/core/validate.py
src/io/__init__.py
src/io/config.py
src/io/converters.py
src/io/csv_loader.py
src/io/holdings.py
src/io/ingest.py
src/io/persist.py
src/io/property.py
src/io/property_loader.py
src/lib/__init__.py
src/lib/currency.py
src/lib/search.py
src/pipeline.py
taxing-0.1.0.dist-info/METADATA
taxing-0.1.0.dist-info/WHEEL
taxing-0.1.0.dist-info/entry_points.txt
taxing-0.1.0.dist-info/RECORD
