Metadata-Version: 2.3
Name: taxing
Version: 0.1.0
Summary: Tax deduction automation for Australian households
License: MIT
Keywords: tax,deductions,capital-gains,australia,automation
Author: Tyson Chan
Author-email: tyson.chan@proton.me
Requires-Python: >=3.11
Classifier: Development Status :: 3 - Alpha
Classifier: Intended Audience :: Developers
Classifier: License :: OSI Approved :: MIT License
Classifier: Programming Language :: Python :: 3
Classifier: Programming Language :: Python :: 3.11
Classifier: Programming Language :: Python :: 3.12
Classifier: Programming Language :: Python :: 3.13
Classifier: Topic :: Office/Business :: Financial
Requires-Dist: ddgs (>=9.0.0,<10.0.0)
Requires-Dist: pandas (>=2.3.0,<3.0.0)
Requires-Dist: pyyaml (>=6.0.3,<7.0.0)
